odoo8_addon_account_invoice_period_usability-8.0.1.0.0.99.dev6-py2.7-nspkg.pth
odoo8_addon_account_invoice_period_usability-8.0.1.0.0.99.dev6.dist-info/METADATA
odoo8_addon_account_invoice_period_usability-8.0.1.0.0.99.dev6.dist-info/RECORD
odoo8_addon_account_invoice_period_usability-8.0.1.0.0.99.dev6.dist-info/WHEEL
odoo8_addon_account_invoice_period_usability-8.0.1.0.0.99.dev6.dist-info/namespace_packages.txt
odoo8_addon_account_invoice_period_usability-8.0.1.0.0.99.dev6.dist-info/top_level.txt
odoo_addons/account_invoice_period_usability/README.rst
odoo_addons/account_invoice_period_usability/__init__.py
odoo_addons/account_invoice_period_usability/__openerp__.py
odoo_addons/account_invoice_period_usability/i18n/account_invoice_period_usability.pot
odoo_addons/account_invoice_period_usability/i18n/de.po
odoo_addons/account_invoice_period_usability/i18n/es.po
odoo_addons/account_invoice_period_usability/i18n/sl.po
odoo_addons/account_invoice_period_usability/i18n/tr.po
odoo_addons/account_invoice_period_usability/static/description/icon.png
odoo_addons/account_invoice_period_usability/views/account_invoice_view.xml
