Metadata-Version: 2.1
Name: odoo8-addon-account-invoice-period-usability
Version: 8.0.1.0.0.99.dev6
Summary: Display in the supplier invoice form the fiscal period
Requires-Dist: odoo (<9.0a,>=8.0a)
